multivelo/__init__.py
multivelo/auxiliary.py
multivelo/dynamical_chrom_func.py
multivelo/mv_logging.py
multivelo/pyWNN.py
multivelo/settings.py
multivelo/steady_chrom_func.py
multivelo/neural_nets/dir0.pt
multivelo/neural_nets/dir1.pt
multivelo/neural_nets/dir2_m1.pt
multivelo/neural_nets/dir2_m2.pt
multivelo-0.1.5.dist-info/LICENSE
multivelo-0.1.5.dist-info/METADATA
multivelo-0.1.5.dist-info/WHEEL
multivelo-0.1.5.dist-info/top_level.txt
multivelo-0.1.5.dist-info/RECORD
