Metadata-Version: 2.1
Name: multivelo
Version: 0.1.5
Summary: Multi-omic extension of single-cell RNA velocity
Home-page: https://github.com/welch-lab/MultiVelo
Author: Chen Li
Author-email: chlseven@umich.edu
License: BSD 3-Clause License
Keywords: RNA velocity,single-cell,transcriptomics,chromatin,epigenetic,epigenomic,gene regulation,multi-omic,dynamical
Classifier: Development Status :: 4 - Beta
Classifier: Intended Audience :: Science/Research
Classifier: License :: OSI Approved :: BSD License
Classifier: Natural Language :: English
Classifier: Operating System :: MacOS :: MacOS X
Classifier: Operating System :: Microsoft :: Windows
Classifier: Operating System :: POSIX :: Linux
Classifier: Programming Language :: Python :: 3
Classifier: Programming Language :: Python :: 3.7
Classifier: Programming Language :: Python :: 3.8
Classifier: Programming Language :: Python :: 3.9
Classifier: Topic :: Scientific/Engineering :: Bio-Informatics
Classifier: Topic :: Scientific/Engineering :: Visualization
Requires-Python: >=3.7
License-File: LICENSE
Requires-Dist: anndata>=0.7.5
Requires-Dist: scanpy>=1.5
Requires-Dist: scvelo>=0.2.3
Requires-Dist: loompy>=2.0.12
Requires-Dist: umap-learn>=0.3.10
Requires-Dist: h5py>=2.10.0
Requires-Dist: numba>=0.41.0
Requires-Dist: numpy>=1.17
Requires-Dist: scipy>=1.4.1
Requires-Dist: pandas>=0.23
Requires-Dist: scikit-learn>=0.23.0
Requires-Dist: matplotlib>=3.3.0
Requires-Dist: seaborn>=0.11.0
Requires-Dist: tqdm
Requires-Dist: joblib
Requires-Dist: ipywidgets<=7.7.1
